odoo/addons/webservice/README.rst
odoo/addons/webservice/__init__.py
odoo/addons/webservice/__manifest__.py
odoo/addons/webservice/utils.py
odoo/addons/webservice/components/__init__.py
odoo/addons/webservice/components/base_adapter.py
odoo/addons/webservice/components/request_adapter.py
odoo/addons/webservice/controllers/__init__.py
odoo/addons/webservice/controllers/oauth2.py
odoo/addons/webservice/i18n/fr.po
odoo/addons/webservice/i18n/it.po
odoo/addons/webservice/i18n/webservice.pot
odoo/addons/webservice/models/__init__.py
odoo/addons/webservice/models/webservice_backend.py
odoo/addons/webservice/readme/CONTRIBUTORS.md
odoo/addons/webservice/readme/DESCRIPTION.md
odoo/addons/webservice/security/ir.model.access.csv
odoo/addons/webservice/security/ir_rule.xml
odoo/addons/webservice/static/description/icon.png
odoo/addons/webservice/static/description/index.html
odoo/addons/webservice/tests/__init__.py
odoo/addons/webservice/tests/common.py
odoo/addons/webservice/tests/test_oauth2.py
odoo/addons/webservice/tests/test_utils.py
odoo/addons/webservice/tests/test_webservice.py
odoo/addons/webservice/views/webservice_backend.xml
odoo_addon_webservice-18.0.1.1.0.2.dist-info/METADATA
odoo_addon_webservice-18.0.1.1.0.2.dist-info/WHEEL
odoo_addon_webservice-18.0.1.1.0.2.dist-info/top_level.txt
odoo_addon_webservice-18.0.1.1.0.2.dist-info/RECORD
