Metadata-Version: 2.1
Name: odoo-addon-webservice
Version: 18.0.1.1.0.2
Requires-Python: >=3.10
Requires-Dist: oauthlib
Requires-Dist: odoo-addon-component==18.0.*
Requires-Dist: odoo-addon-server_environment==18.0.*
Requires-Dist: odoo==18.0.*
Requires-Dist: requests-oauthlib
Requires-Dist: responses
Summary: Defines webservice abstract definition to be used generally
Home-page: https://github.com/OCA/web-api
License: AGPL-3
Author: Creu Blanca, Camptocamp, Odoo Community Association (OCA)
Author-email: support@odoo-community.org
Classifier: Programming Language :: Python
Classifier: Framework :: Odoo
Classifier: Framework :: Odoo :: 18.0
Classifier: License :: OSI Approved :: GNU Affero General Public License v3
Classifier: Development Status :: 5 - Production/Stable
